django_dropbox_storage/__init__.py
django_dropbox_storage/models.py
django_dropbox_storage/settings.py
django_dropbox_storage/storage.py
django_dropbox_storage/tests.py
django_dropbox_storage/views.py
django_dropbox_storage/management/__init__.py
django_dropbox_storage/management/commands/__init__.py
django_dropbox_storage/management/commands/get_dropbox_token.py
django_dropbox_storage_fork-0.4.2.dist-info/LICENSE.txt
django_dropbox_storage_fork-0.4.2.dist-info/METADATA
django_dropbox_storage_fork-0.4.2.dist-info/WHEEL
django_dropbox_storage_fork-0.4.2.dist-info/top_level.txt
django_dropbox_storage_fork-0.4.2.dist-info/RECORD
