Metadata-Version: 2.1
Name: django-dropbox-storage-fork
Version: 0.4.2
Summary: A Dropbox Storage for your Django apps
Home-page: https://github.com/ryesalvador/django-dropbox-storage
Author: Emanuele Bertoldi
Author-email: emanuele.bertoldi@gmail.com
License: MIT
Download-URL: https://github.com/ryesalvador/django-dropbox-storage/archive/0.4.2.tar.gz
Keywords: django storage dropbox
Platform: UNKNOWN
Requires-Dist: django (>=3.1.4)
Requires-Dist: dropbox (>=11.0.0)
